float1234/__init__.py
float1234/wp.py
float1234/wp2.py
float1234-1.1.dist-info/LICENSE
float1234-1.1.dist-info/METADATA
float1234-1.1.dist-info/WHEEL
float1234-1.1.dist-info/top_level.txt
float1234-1.1.dist-info/RECORD
