Metadata-Version: 2.1
Name: float1234
Version: 1.1
Summary: 一个很NB的包
Home-page: UNKNOWN
Author: xxx
Author-email: wanghaoming17@163.com
License: UNKNOWN
Platform: UNKNOWN
Classifier: Programming Language :: Python :: 3
Classifier: License :: OSI Approved :: MIT License
Requires-Python: >=3
License-File: LICENSE
Requires-Dist: pillow
